pyrelogios/__init__.py
pyrelogios/relogio_analogico.py
pyrelogios/relogio_digital.py
pyrelogios/RelogioPalmeiras2.gif
pyrelogios-0.1.0.dist-info/WHEEL
pyrelogios-0.1.0.dist-info/METADATA
pyrelogios-0.1.0.dist-info/RECORD
