Metadata-Version: 2.1
Name: pyrelogios
Version: 0.1.0
Summary: Publicação de teste PyRelogios
Author: vlademir
Author-email: vlade@gmail.com
Requires-Python: >=3.9,<4.0
Classifier: Programming Language :: Python :: 3
Classifier: Programming Language :: Python :: 3.10
Classifier: Programming Language :: Python :: 3.9
